dataframe_to_online_spreadsheet/__init__.py
dataframe_to_online_spreadsheet/feishu.py
dataframe_to_online_spreadsheet/wecom.py
dataframe_to_online_spreadsheet-0.1.15.dist-info/METADATA
dataframe_to_online_spreadsheet-0.1.15.dist-info/WHEEL
dataframe_to_online_spreadsheet-0.1.15.dist-info/licenses/LICENSE
dataframe_to_online_spreadsheet-0.1.15.dist-info/RECORD
