Metadata-Version: 2.4
Name: dataframe_to_online_spreadsheet
Version: 0.1.15
Summary: Export a pandas dataframe to a online spreadsheet.
Project-URL: Homepage, https://github.com/kafkaliu/dataframe_to_online_spreadsheet
Project-URL: Issues, https://github.com/kafkaliu/dataframe_to_online_spreadsheet/issues
Author-email: Kafka Liu <kafka.liu@gmail.com>
License: Apache-2.0
License-File: LICENSE
Classifier: License :: OSI Approved :: Apache Software License
Classifier: Operating System :: OS Independent
Classifier: Programming Language :: Python :: 3
Requires-Python: >=3.8
Requires-Dist: pandas>=1.0.0
Requires-Dist: requests>=2.0.0
